yolo_dataset_db_manager/__init__.py
yolo_dataset_db_manager/db/__init__.py
yolo_dataset_db_manager/db/abstract.py
yolo_dataset_db_manager/db/postgresql.py
yolo_dataset_db_manager/processor.py
yolo_dataset_db_manager/settings.py
yolodatasetdbmanager-0.2.1.dist-info/METADATA
yolodatasetdbmanager-0.2.1.dist-info/WHEEL
yolodatasetdbmanager-0.2.1.dist-info/entry_points.txt
yolodatasetdbmanager-0.2.1.dist-info/licenses/LICENSE
yolodatasetdbmanager-0.2.1.dist-info/RECORD
