Metadata-Version: 2.1
Name: YoloDatasetDBManager
Version: 0.2.1
Summary: A Python library for managing YOLO datasets, allowing seamless conversion between filesystem-based datasets and PostgreSQL storage. Features include inserting datasets into a database, retrieving and rebuilding datasets, and preserving YOLO-compliant folder structures.
Author-Email: Macktireh <abdimack97@gmail.com>
License: MIT
Classifier: Programming Language :: Python
Classifier: Programming Language :: Python :: 3
Classifier: Programming Language :: Python :: 3.11
Classifier: Programming Language :: Python :: 3.12
Classifier: Programming Language :: Python :: 3.13
Classifier: License :: OSI Approved :: MIT License
Classifier: Operating System :: OS Independent
Classifier: Intended Audience :: Developers
Classifier: Typing :: Typed
Classifier: Topic :: Software Development :: Libraries
Project-URL: Homepage, https://github.com/Macktireh/YoloDatasetDBManager
Project-URL: Documentation, https://github.com/Macktireh/YoloDatasetDBManager#readme
Project-URL: Repository, https://github.com/Macktireh/YoloDatasetDBManager
Project-URL: Issues, https://github.com/Macktireh/YoloDatasetDBManager/issues
Requires-Python: >=3.11
Requires-Dist: psycopg[binary]>=3.2.3
Requires-Dist: pydantic>=2.9.2
Requires-Dist: python-dotenv>=1.0.1
Requires-Dist: rich>=13.9.4
